quetz_sql_authenticator/__init__.py
quetz_sql_authenticator/api.py
quetz_sql_authenticator/db_models.py
quetz_sql_authenticator/main.py
quetz_sql_authenticator/migrations/__init__.py
quetz_sql_authenticator/migrations/versions/__init__.py
quetz_sql_authenticator/migrations/versions/db1fe7199ca1_.py
quetz_sql_authenticator-0.0.5.dist-info/LICENSE
quetz_sql_authenticator-0.0.5.dist-info/METADATA
quetz_sql_authenticator-0.0.5.dist-info/WHEEL
quetz_sql_authenticator-0.0.5.dist-info/entry_points.txt
quetz_sql_authenticator-0.0.5.dist-info/top_level.txt
quetz_sql_authenticator-0.0.5.dist-info/RECORD
