Metadata-Version: 2.1
Name: quetz-sql-authenticator
Version: 0.0.5
Summary: Manage simple credentials for your Quetz server
Home-page: https://github.com/mamba-org/quetz-sql-authenticator
Author: QuantStack & Quetz contributors
Author-email: wolf.vollprecht@quantstack.net
Classifier: Programming Language :: Python :: 3
Classifier: Programming Language :: Python :: 3.8
Classifier: Programming Language :: Python :: 3.9
Classifier: Programming Language :: Python :: 3.10
Requires-Python: >=3.8
License-File: LICENSE
Requires-Dist: setuptools (>=3.0)
Requires-Dist: quetz-server (>=0.4.4)
Requires-Dist: sqlalchemy
Requires-Dist: fastapi
Requires-Dist: alembic
Requires-Dist: passlib
